kmboxnet/__init__.py
kmboxnet/hidtable.py
kmboxnet/kmbox.py
kmboxnet/monitor.py
kmboxnet-0.2.5.dist-info/METADATA
kmboxnet-0.2.5.dist-info/WHEEL
kmboxnet-0.2.5.dist-info/top_level.txt
kmboxnet-0.2.5.dist-info/RECORD
