Metadata-Version: 2.4
Name: kmboxnet
Version: 0.2.5
Summary: Prototype of a controller library for Kmbox Net. Depends only on Python standard libraries. Implemented using Python's socket module.
Author: yuta6
Requires-Python: >=3.8
